{
  "id": "examples/table-01",
  "name": "Table",
  "registryDependencies": [
    "ui/table"
  ],
  "files": [
    {
      "path": "examples/table-01.tsx",
      "content": "import * as React from \"react\";\nimport { css } from \"@pigment-css/react\";\n\nimport { Table, TableBody, TableCell, TableHeader, TableHeaderCell, TableRow } from \"@/components/ui/table\";\n\ntype Row = {\n  id: string;\n  displayId: number;\n  customer: string;\n  email: string;\n  amount: number;\n  currency: string;\n};\n\nconst rows: Row[] = [\n  {\n    id: \"order_6782\",\n    displayId: 86078,\n    customer: \"Jill Miller\",\n    email: \"32690@gmail.com\",\n    amount: 493,\n    currency: \"EUR\",\n  },\n  {\n    id: \"order_46487\",\n    displayId: 42845,\n    customer: \"Sarah Garcia\",\n    email: \"86379@gmail.com\",\n    amount: 113,\n    currency: \"JPY\",\n  },\n  {\n    id: \"order_8169\",\n    displayId: 39129,\n    customer: \"Josef Smith\",\n    email: \"89383@gmail.com\",\n    amount: 43,\n    currency: \"USD\",\n  },\n  {\n    id: \"order_67883\",\n    displayId: 5548,\n    customer: \"Elvis Jones\",\n    email: \"52860@gmail.com\",\n    amount: 840,\n    currency: \"GBP\",\n  },\n  {\n    id: \"order_61121\",\n    displayId: 87668,\n    customer: \"Charles Rodriguez\",\n    email: \"45675@gmail.com\",\n    amount: 304,\n    currency: \"GBP\",\n  },\n];\n\nexport default function TableExample(): JSX.Element {\n  return (\n    <Table className={css({ maxWidth: \"800px\", marginLeft: \"auto\", marginRight: \"auto\", width: \"var(--size-full)\" })}>\n      <TableHeader>\n        <TableRow>\n          <TableHeaderCell>#</TableHeaderCell>\n          <TableHeaderCell>Customer</TableHeaderCell>\n          <TableHeaderCell>Email</TableHeaderCell>\n          <TableHeaderCell className={css({ textAlign: \"right\" })}>Amount</TableHeaderCell>\n          <TableHeaderCell></TableHeaderCell>\n        </TableRow>\n      </TableHeader>\n      <TableBody>\n        {rows.map((order) => {\n          return (\n            <TableRow key={order.id}>\n              <TableCell>{order.displayId}</TableCell>\n              <TableCell>{order.customer}</TableCell>\n              <TableCell>{order.email}</TableCell>\n              <TableCell className={css({ textAlign: \"right\" })}>\n                {new Intl.NumberFormat(\"en-US\", {\n                  style: \"currency\",\n                  currency: order.currency,\n                }).format(order.amount)}\n              </TableCell>\n              <TableCell className=\"text-ui-fg-muted\">{order.currency}</TableCell>\n            </TableRow>\n          );\n        })}\n      </TableBody>\n    </Table>\n  );\n}\n"
    }
  ]
}